setup.py
commonpi.egg-info/PKG-INFO
commonpi.egg-info/SOURCES.txt
commonpi.egg-info/dependency_links.txt
commonpi.egg-info/requires.txt
commonpi.egg-info/top_level.txt
commonpi/lib/Context.py
commonpi/lib/ReplaceVariable.py
commonpi/lib/__init__.py
commonpi/lib/api.py
commonpi/lib/cookie_ui.py
commonpi/lib/newReport.py
commonpi/lib/parsley.py
commonpi/lib/public.py
commonpi/lib/readexcel.py
commonpi/lib/sendmail.py
commonpi/lib/utility.py
commonpi/lib/writeexcel.py
commonpi/package/HTMLTestRunner.py
commonpi/package/__init__.py