Metadata-Version: 1.0
Name: commonpi
Version: 2.2.0
Summary: commonpi
Home-page: UNKNOWN
Author: cxx
Author-email: cuixiaoxia@chinasofti.com
License: UNKNOWN
Platform: UNKNOWN
